Workbook

Sheet Instructions
A1: TIB SYSTEMS LLC | SAP Controls Project Foundation Workbook Set
A2: W03 — Module & Business Process Scope
A4: Purpose
A5: Separates the SAP module from the business process and ties each process to its systems, interfaces and the financial statement areas it affects. The BP-ID created here anchors every risk in W04.
A7: How to use this workbook
A8: 1. Start from the financial statements: enter significant accounts in FSLI_Map.
A9: 2. Map each account to the process that creates its balance; break each process into sub-processes with a BP-ID in Process_Scope.
A10: 3. Record modules, SYS-IDs (W01), INT-IDs (W02), owners and indicative transactions.
A11: 4. Add the technical areas BP-TECH-01 to 03 in Technical_Areas.
A12: 5. Mark confirmation status honestly. Unspecified processes are Outstanding, never guessed.
A14: Colour legend
A15: Yellow cells with blue text = you enter data here. Grey cells = formulas (do not overwrite). Row 5 of each register is a worked ABC Manufacturing example: overwrite it with your first record.
... A26: Column dictionary
A27: Tab | B27: Field | C27: Definition | D27: Allowed values / rule | E27: Type
A28: Process_Scope | B28: BP-ID | C28: Unique key for the sub-process | D28: BP-…; unique | E28: Input
A29: Process_Scope | B29: Business process | C29: End-to-end process | D29: R2R / P2P / O2C / INV / H2R / TECH | E29: Input
A30: Process_Scope | B30: Sub-process | C30: Specific activity within the process | D30: Free text | E30: Input
A31: Process_Scope | B31: Module(s) | C31: SAP modules or functional areas used | D31: FI, CO, MM, SD, HCM, Basis/Security | E31: Input
A32: Process_Scope | B32: Supporting SYS-ID(s) | C32: Systems the sub-process runs on | D32: SYS-IDs from W01 | E32: Input
A33: Process_Scope | B33: Related INT-ID(s) | C33: Interfaces feeding the sub-process | D33: INT-IDs from W02 | E33: Input
A34: Process_Scope | B34: Significant FSLI / accounts | C34: Financial statement areas affected | D34: From FSLI_Map | E34: Input
A35: Process_Scope | B35: Significance | C35: Why it matters to the audit | D35: High / Medium / Low | E35: Input
A36: Process_Scope | B36: In scope? | C36: Included in engagement | D36: Y / N / TBC | E36: Input
A37: Process_Scope | B37: Process owner | C37: Accountable business owner | D37: Name / role; TBC allowed | E37: Input
A38: Process_Scope | B38: Indicative transactions | C38: Key t-codes / Fiori apps | D38: Used later for SoD and access testing | E38: Input
... A71: Open_Items | B71: Resolution | C71: How it was resolved | D71: Free text | E71: Input
A73: Version history
A74: 0.1 — October 2026 — initial template (TIB Systems LLC)
A75: Cross-workbook links: keys from other workbooks are pasted as values into the Ref_ tabs, so this file works on its own and never breaks when files are moved.

Sheet Process_Scope
A1: W03 — Process Scope
A2: One row per business sub-process. Row 5 is a worked example. Overwrite it.
A4: BP-ID | B4: Business process | C4: Sub-process | D4: Module(s) | E4: Supporting SYS-ID(s) | F4: Related INT-ID(s) | G4: Significant FSLI / accounts | H4: Significance | I4: In scope? | J4: Process owner | K4: Indicative transactions | L4: Confirmation status | M4: Scoping note | N4: Row check
A5: BP-P2P-02 | B5: P2P | C5: Purchasing, receipt and invoice | D5: MM, FI | E5: SYS-03 | G5: Trade payables; Inventory | H5: High | I5: Y | J5: Head of AP | K5: ME21N, MIGO, MIRO | L5: Source-identified | N5: =IF(A5="","",IF(LEFT(A5,3)<>"BP-","Key must start BP-",IF(OR(B5="",C5="",D5=""),"Process, sub-process and module needed",IF(AND(I5="Y",E5=""),"Supporting SYS-ID needed",IF(AND(OR(I5="N",L5="Outstanding"),M5=""),"Note the rationale / open question","OK"))))) -> OK
N6: =IF(A6="","",IF(LEFT(A6,3)<>"BP-","Key must start BP-",IF(OR(B6="",C6="",D6=""),"Process, sub-process and module needed",IF(AND(I6="Y",E6=""),"Supporting SYS-ID needed",IF(AND(OR(I6="N",L6="Outstanding"),M6=""),"Note the rationale / open question","OK")))))
N7: =IF(A7="","",IF(LEFT(A7,3)<>"BP-","Key must start BP-",IF(OR(B7="",C7="",D7=""),"Process, sub-process and module needed",IF(AND(I7="Y",E7=""),"Supporting SYS-ID needed",IF(AND(OR(I7="N",L7="Outstanding"),M7=""),"Note the rationale / open question","OK")))))
N8: =IF(A8="","",IF(LEFT(A8,3)<>"BP-","Key must start BP-",IF(OR(B8="",C8="",D8=""),"Process, sub-process and module needed",IF(AND(I8="Y",E8=""),"Supporting SYS-ID needed",IF(AND(OR(I8="N",L8="Outstanding"),M8=""),"Note the rationale / open question","OK")))))
N9: =IF(A9="","",IF(LEFT(A9,3)<>"BP-","Key must start BP-",IF(OR(B9="",C9="",D9=""),"Process, sub-process and module needed",IF(AND(I9="Y",E9=""),"Supporting SYS-ID needed",IF(AND(OR(I9="N",L9="Outstanding"),M9=""),"Note the rationale / open question","OK")))))
N10: =IF(A10="","",IF(LEFT(A10,3)<>"BP-","Key must start BP-",IF(OR(B10="",C10="",D10=""),"Process, sub-process and module needed",IF(AND(I10="Y",E10=""),"Supporting SYS-ID needed",IF(AND(OR(I10="N",L10="Outstanding"),M10=""),"Note the rationale / open question","OK")))))
N11: =IF(A11="","",IF(LEFT(A11,3)<>"BP-","Key must start BP-",IF(OR(B11="",C11="",D11=""),"Process, sub-process and module needed",IF(AND(I11="Y",E11=""),"Supporting SYS-ID needed",IF(AND(OR(I11="N",L11="Outstanding"),M11=""),"Note the rationale / open question","OK")))))
N12: =IF(A12="","",IF(LEFT(A12,3)<>"BP-","Key must start BP-",IF(OR(B12="",C12="",D12=""),"Process, sub-process and module needed",IF(AND(I12="Y",E12=""),"Supporting SYS-ID needed",IF(AND(OR(I12="N",L12="Outstanding"),M12=""),"Note the rationale / open question","OK")))))
N13: =IF(A13="","",IF(LEFT(A13,3)<>"BP-","Key must start BP-",IF(OR(B13="",C13="",D13=""),"Process, sub-process and module needed",IF(AND(I13="Y",E13=""),"Supporting SYS-ID needed",IF(AND(OR(I13="N",L13="Outstanding"),M13=""),"Note the rationale / open question","OK")))))
N14: =IF(A14="","",IF(LEFT(A14,3)<>"BP-","Key must start BP-",IF(OR(B14="",C14="",D14=""),"Process, sub-process and module needed",IF(AND(I14="Y",E14=""),"Supporting SYS-ID needed",IF(AND(OR(I14="N",L14="Outstanding"),M14=""),"Note the rationale / open question","OK")))))
N15: =IF(A15="","",IF(LEFT(A15,3)<>"BP-","Key must start BP-",IF(OR(B15="",C15="",D15=""),"Process, sub-process and module needed",IF(AND(I15="Y",E15=""),"Supporting SYS-ID needed",IF(AND(OR(I15="N",L15="Outstanding"),M15=""),"Note the rationale / open question","OK")))))
N16: =IF(A16="","",IF(LEFT(A16,3)<>"BP-","Key must start BP-",IF(OR(B16="",C16="",D16=""),"Process, sub-process and module needed",IF(AND(I16="Y",E16=""),"Supporting SYS-ID needed",IF(AND(OR(I16="N",L16="Outstanding"),M16=""),"Note the rationale / open question","OK")))))
N17: =IF(A17="","",IF(LEFT(A17,3)<>"BP-","Key must start BP-",IF(OR(B17="",C17="",D17=""),"Process, sub-process and module needed",IF(AND(I17="Y",E17=""),"Supporting SYS-ID needed",IF(AND(OR(I17="N",L17="Outstanding"),M17=""),"Note the rationale / open question","OK")))))
... N204: =IF(A204="","",IF(LEFT(A204,3)<>"BP-","Key must start BP-",IF(OR(B204="",C204="",D204=""),"Process, sub-process and module needed",IF(AND(I204="Y",E204=""),"Supporting SYS-ID needed",IF(AND(OR(I204="N",L204="Outstanding"),M204=""),"Note the rationale / open question","OK")))))

Sheet Technical_Areas
A1: W03 — Technical Areas
A2: Basis/Security areas treated as processes for ITGC purposes (BP-TECH-nn).
A4: BP-ID | B4: Business process | C4: Sub-process | D4: Module(s) | E4: Supporting SYS-ID(s) | F4: Related INT-ID(s) | G4: Significant FSLI / accounts | H4: Significance | I4: In scope? | J4: Process owner | K4: Indicative transactions | L4: Confirmation status | M4: Scoping note | N4: Row check
A5: BP-TECH-01 | B5: TECH | C5: User administration and access | D5: Basis/Security | E5: SYS-03, SYS-04, SYS-06 | F5: INT-04 | G5: All financial accounts | H5: High | I5: Y | J5: IT Security Manager | K5: SU01, PFCG, GRC ARM | L5: Confirmed | N5: =IF(A5="","",IF(LEFT(A5,8)<>"BP-TECH-","Key must start BP-TECH-",IF(OR(B5="",C5="",D5=""),"Process, sub-process and module needed",IF(AND(I5="Y",E5=""),"Supporting SYS-ID needed",IF(AND(OR(I5="N",L5="Outstanding"),M5=""),"Note the rationale / open question","OK"))))) -> OK
N6: =IF(A6="","",IF(LEFT(A6,8)<>"BP-TECH-","Key must start BP-TECH-",IF(OR(B6="",C6="",D6=""),"Process, sub-process and module needed",IF(AND(I6="Y",E6=""),"Supporting SYS-ID needed",IF(AND(OR(I6="N",L6="Outstanding"),M6=""),"Note the rationale / open question","OK")))))
N7: =IF(A7="","",IF(LEFT(A7,8)<>"BP-TECH-","Key must start BP-TECH-",IF(OR(B7="",C7="",D7=""),"Process, sub-process and module needed",IF(AND(I7="Y",E7=""),"Supporting SYS-ID needed",IF(AND(OR(I7="N",L7="Outstanding"),M7=""),"Note the rationale / open question","OK")))))
N8: =IF(A8="","",IF(LEFT(A8,8)<>"BP-TECH-","Key must start BP-TECH-",IF(OR(B8="",C8="",D8=""),"Process, sub-process and module needed",IF(AND(I8="Y",E8=""),"Supporting SYS-ID needed",IF(AND(OR(I8="N",L8="Outstanding"),M8=""),"Note the rationale / open question","OK")))))
N9: =IF(A9="","",IF(LEFT(A9,8)<>"BP-TECH-","Key must start BP-TECH-",IF(OR(B9="",C9="",D9=""),"Process, sub-process and module needed",IF(AND(I9="Y",E9=""),"Supporting SYS-ID needed",IF(AND(OR(I9="N",L9="Outstanding"),M9=""),"Note the rationale / open question","OK")))))
N10: =IF(A10="","",IF(LEFT(A10,8)<>"BP-TECH-","Key must start BP-TECH-",IF(OR(B10="",C10="",D10=""),"Process, sub-process and module needed",IF(AND(I10="Y",E10=""),"Supporting SYS-ID needed",IF(AND(OR(I10="N",L10="Outstanding"),M10=""),"Note the rationale / open question","OK")))))
N11: =IF(A11="","",IF(LEFT(A11,8)<>"BP-TECH-","Key must start BP-TECH-",IF(OR(B11="",C11="",D11=""),"Process, sub-process and module needed",IF(AND(I11="Y",E11=""),"Supporting SYS-ID needed",IF(AND(OR(I11="N",L11="Outstanding"),M11=""),"Note the rationale / open question","OK")))))
N12: =IF(A12="","",IF(LEFT(A12,8)<>"BP-TECH-","Key must start BP-TECH-",IF(OR(B12="",C12="",D12=""),"Process, sub-process and module needed",IF(AND(I12="Y",E12=""),"Supporting SYS-ID needed",IF(AND(OR(I12="N",L12="Outstanding"),M12=""),"Note the rationale / open question","OK")))))
N13: =IF(A13="","",IF(LEFT(A13,8)<>"BP-TECH-","Key must start BP-TECH-",IF(OR(B13="",C13="",D13=""),"Process, sub-process and module needed",IF(AND(I13="Y",E13=""),"Supporting SYS-ID needed",IF(AND(OR(I13="N",L13="Outstanding"),M13=""),"Note the rationale / open question","OK")))))
N14: =IF(A14="","",IF(LEFT(A14,8)<>"BP-TECH-","Key must start BP-TECH-",IF(OR(B14="",C14="",D14=""),"Process, sub-process and module needed",IF(AND(I14="Y",E14=""),"Supporting SYS-ID needed",IF(AND(OR(I14="N",L14="Outstanding"),M14=""),"Note the rationale / open question","OK")))))
N15: =IF(A15="","",IF(LEFT(A15,8)<>"BP-TECH-","Key must start BP-TECH-",IF(OR(B15="",C15="",D15=""),"Process, sub-process and module needed",IF(AND(I15="Y",E15=""),"Supporting SYS-ID needed",IF(AND(OR(I15="N",L15="Outstanding"),M15=""),"Note the rationale / open question","OK")))))
N16: =IF(A16="","",IF(LEFT(A16,8)<>"BP-TECH-","Key must start BP-TECH-",IF(OR(B16="",C16="",D16=""),"Process, sub-process and module needed",IF(AND(I16="Y",E16=""),"Supporting SYS-ID needed",IF(AND(OR(I16="N",L16="Outstanding"),M16=""),"Note the rationale / open question","OK")))))
N17: =IF(A17="","",IF(LEFT(A17,8)<>"BP-TECH-","Key must start BP-TECH-",IF(OR(B17="",C17="",D17=""),"Process, sub-process and module needed",IF(AND(I17="Y",E17=""),"Supporting SYS-ID needed",IF(AND(OR(I17="N",L17="Outstanding"),M17=""),"Note the rationale / open question","OK")))))
... N204: =IF(A204="","",IF(LEFT(A204,8)<>"BP-TECH-","Key must start BP-TECH-",IF(OR(B204="",C204="",D204=""),"Process, sub-process and module needed",IF(AND(I204="Y",E204=""),"Supporting SYS-ID needed",IF(AND(OR(I204="N",L204="Outstanding"),M204=""),"Note the rationale / open question","OK")))))

Sheet FSLI_Map
A1: W03 — FSLI Map
A2: Significant accounts mapped to processes.
A4: FSLI ID | B4: FSLI / account | C4: Significant? | D4: Primary process | E4: Mapped BP-ID(s) | F4: Assertions | G4: Note | H4: Check
A5: FSLI-02 | B5: Trade payables | C5: Y | D5: P2P | E5: BP-P2P-01, BP-P2P-02, BP-P2P-03 | F5: Completeness, Occurrence | H5: =IF(A5="","",IF(AND(C5="Y",E5=""),"Map to a BP-ID","OK")) -> OK
H6: =IF(A6="","",IF(AND(C6="Y",E6=""),"Map to a BP-ID","OK"))
H7: =IF(A7="","",IF(AND(C7="Y",E7=""),"Map to a BP-ID","OK"))
H8: =IF(A8="","",IF(AND(C8="Y",E8=""),"Map to a BP-ID","OK"))
H9: =IF(A9="","",IF(AND(C9="Y",E9=""),"Map to a BP-ID","OK"))
H10: =IF(A10="","",IF(AND(C10="Y",E10=""),"Map to a BP-ID","OK"))
H11: =IF(A11="","",IF(AND(C11="Y",E11=""),"Map to a BP-ID","OK"))
H12: =IF(A12="","",IF(AND(C12="Y",E12=""),"Map to a BP-ID","OK"))
H13: =IF(A13="","",IF(AND(C13="Y",E13=""),"Map to a BP-ID","OK"))
H14: =IF(A14="","",IF(AND(C14="Y",E14=""),"Map to a BP-ID","OK"))
H15: =IF(A15="","",IF(AND(C15="Y",E15=""),"Map to a BP-ID","OK"))
H16: =IF(A16="","",IF(AND(C16="Y",E16=""),"Map to a BP-ID","OK"))
H17: =IF(A17="","",IF(AND(C17="Y",E17=""),"Map to a BP-ID","OK"))
... H204: =IF(A204="","",IF(AND(C204="Y",E204=""),"Map to a BP-ID","OK"))

Sheet Open_Items
A1: W03 — Open Items
A2: Processes or owners still to confirm.
A4: Item ID | B4: Source | C4: Question / dependency | D4: Owner | E4: Raised | F4: Target date | G4: Status | H4: Resolution
A5: OI-01 | B5: BP-H2R-01 | C5: HR business process not specified in source: confirm payroll posting scope. | D5: HR Manager | G5: Open

Sheet BP_Index
A1: BP_Index — all BP-IDs (formula)
A2: Combines Process_Scope and Technical_Areas. Copy column A (values only) into W04 Ref_BP.
A4: BP-ID
A5: =IF(Process_Scope!A5="","",Process_Scope!A5) -> BP-P2P-02
A6: =IF(Process_Scope!A6="","",Process_Scope!A6)
A7: =IF(Process_Scope!A7="","",Process_Scope!A7)
A8: =IF(Process_Scope!A8="","",Process_Scope!A8)
A9: =IF(Process_Scope!A9="","",Process_Scope!A9)
A10: =IF(Process_Scope!A10="","",Process_Scope!A10)
A11: =IF(Process_Scope!A11="","",Process_Scope!A11)
A12: =IF(Process_Scope!A12="","",Process_Scope!A12)
A13: =IF(Process_Scope!A13="","",Process_Scope!A13)
A14: =IF(Process_Scope!A14="","",Process_Scope!A14)
A15: =IF(Process_Scope!A15="","",Process_Scope!A15)
A16: =IF(Process_Scope!A16="","",Process_Scope!A16)
... A154: =IF(Process_Scope!A154="","",Process_Scope!A154)
A155: =IF(Technical_Areas!A5="","",Technical_Areas!A5) -> BP-TECH-01
A156: =IF(Technical_Areas!A6="","",Technical_Areas!A6)
A157: =IF(Technical_Areas!A7="","",Technical_Areas!A7)
A158: =IF(Technical_Areas!A8="","",Technical_Areas!A8)
A159: =IF(Technical_Areas!A9="","",Technical_Areas!A9)
A160: =IF(Technical_Areas!A10="","",Technical_Areas!A10)
A161: =IF(Technical_Areas!A11="","",Technical_Areas!A11)
A162: =IF(Technical_Areas!A12="","",Technical_Areas!A12)
A163: =IF(Technical_Areas!A13="","",Technical_Areas!A13)
A164: =IF(Technical_Areas!A14="","",Technical_Areas!A14)
A165: =IF(Technical_Areas!A15="","",Technical_Areas!A15)
A166: =IF(Technical_Areas!A16="","",Technical_Areas!A16)
... A204: =IF(Technical_Areas!A54="","",Technical_Areas!A54)

Sheet Lists
A1: Proc | B1: Sig | C1: YN | D1: YNT | E1: Conf | F1: OpenStatus
A2: R2R | B2: High | C2: Y | D2: Y | E2: Source-identified | F2: Open
A3: P2P | B3: Medium | C3: N | D3: N | E3: Confirmed | F3: In progress
A4: O2C | B4: Low | D4: TBC | E4: Partially confirmed | F4: Closed
A5: INV | E5: Outstanding
A6: H2R
A7: TECH

Sheet Checks
A1: W03 — Completion checks
A2: All checks are formulas. A workbook passes its gate when every status reads PASS (INFO rows are counts for your information).
A3: Overall | B3: =IF(COUNTIF(C6:C15,"REVIEW")=0,"ALL CHECKS PASS","REVIEW ITEMS: "&COUNTIF(C6:C15,"REVIEW")) -> ALL CHECKS PASS
A5: Check | B5: Count | C5: Status | D5: What to do if REVIEW
A6: Business sub-processes listed | B6: =COUNTA(Process_Scope!A5:A204) -> 1 | C6: INFO | D6: —
A7: Technical areas listed (BP-TECH) | B7: =COUNTA(Technical_Areas!A5:A204) -> 1 | C7: =IF(B7>0,"PASS","REVIEW") -> PASS | D7: Add BP-TECH-01 to 03 so ITGC risks have an anchor.
A8: Duplicate BP-IDs (Process_Scope) | B8: =SUMPRODUCT((Process_Scope!A5:A204<>"")*(COUNTIF(Process_Scope!A5:A204,Process_Scope!A5:A204)>1)) -> 0 | C8: =IF(B8=0,"PASS","REVIEW") -> PASS | D8: Keys must be unique.
A9: Duplicate BP-IDs (Technical_Areas) | B9: =SUMPRODUCT((Technical_Areas!A5:A204<>"")*(COUNTIF(Technical_Areas!A5:A204,Technical_Areas!A5:A204)>1)) -> 0 | C9: =IF(B9=0,"PASS","REVIEW") -> PASS | D9: Keys must be unique.
A10: Rows needing attention (Process_Scope) | B10: =SUMPRODUCT((Process_Scope!N5:N204<>"")*(Process_Scope!N5:N204<>"OK")*(LEFT(Process_Scope!N5:N204,2)<>"OK")) -> 0 | C10: =IF(B10=0,"PASS","REVIEW") -> PASS | D10: Read the Row check column.
A11: Rows needing attention (Technical_Areas) | B11: =SUMPRODUCT((Technical_Areas!N5:N204<>"")*(Technical_Areas!N5:N204<>"OK")*(LEFT(Technical_Areas!N5:N204,2)<>"OK")) -> 0 | C11: =IF(B11=0,"PASS","REVIEW") -> PASS | D11: Read the Row check column.
A12: In-scope rows with no supporting system | B12: =SUMPRODUCT((Process_Scope!I5:I204="Y")*(Process_Scope!E5:E204="")) -> 0 | C12: =IF(B12=0,"PASS","REVIEW") -> PASS | D12: Record SYS-IDs from W01.
A13: Rows still Outstanding / TBC scope | B13: =COUNTIF(Process_Scope!L5:L204,"Outstanding")+COUNTIF(Process_Scope!I5:I204,"TBC") -> 0 | C13: INFO | D13: Do not invent processes; chase confirmation (gate G2).
A14: Significant FSLIs not mapped to a process | B14: =COUNTIF(FSLI_Map!H5:H204,"Map*") -> 0 | C14: =IF(B14=0,"PASS","REVIEW") -> PASS | D14: Every significant account needs a process.
A15: FSLIs recorded | B15: =COUNTA(FSLI_Map!A5:A204) -> 1 | C15: =IF(B15>0,"PASS","REVIEW") -> PASS | D15: Start from the audit plan / management scoping.
